{
  "openapi": "3.0.2",
  "info": {
    "title": "Smart Forms Launcher Server for the Aboriginal and Torres Strait Islander Health Check",
    "description": "This CapabilityStatement describes the expected capabilities for systems to launch and exchange data with the [Smart Forms client application](CapabilityStatement-SmartFormsApplication.html) to support the [Aboriginal and Torres Strait Islander Health Check](Questionnaire-AboriginalTorresStraitIslanderHealthCheck.html). It lists the server\u0027s conformance expectations for the resource types required as a launch context, resource types required to support prepopulation of the form, and QuestionnaireResponse requirements for managing form responses. These expectations include supported FHIR profiles, RESTful operations, and search parameters.",
    "license": {
      "name": "Creative Commons Attribution Share Alike 4.0 International",
      "url": "http://spdx.org/licenses/CC-BY-SA-4.0.html"
    },
    "version": "0.2.0",
    "contact": {
      "name": "AEHRC CSIRO",
      "url": "https://confluence.csiro.au/display/PCDQFPhase2/Primary+Care+Data+Quality+Foundations+-+Phase+2"
    }
  },
  "externalDocs": {
    "url": "https://smartforms.csiro.au/ig/CapabilityStatement/SFLauncherServerAboriginalTorresStraitIslanderHealthCheck",
    "description": "FHIR CapabilityStatement"
  },
  "paths": {
    "/metadata": {
      "summary": "Access to the Server\u0027s Capability Statement",
      "description": "All FHIR Servers return a CapabilityStatement that describes what services they perform",
      "get": {
        "summary": "Return the server\u0027s capability statement",
        "operationId": "metadata",
        "responses": {
          "default": {
            "description": "Error, with details",
            "content": {
              "application/fhir+json": {
                "schema": {
                  "$ref": "https://hl7.org/fhir/R4/fhir.schema.json#/definitions/OperationOutcome"
                }
              }
            }
          },
          "200": {
            "description": "the capbility statement",
            "content": {
              "application/fhir+json": {
                "schema": {
                  "$ref": "https://hl7.org/fhir/R4/fhir.schema.json#/definitions/CapabilityStatement"
                }
              }
            }
          }
        },
        "parameters": [
          {
            "$ref": "#/components/parameters/format"
          },
          {
            "$ref": "#/components/parameters/pretty"
          },
          {
            "$ref": "#/components/parameters/summary"
          },
          {
            "$ref": "#/components/parameters/elements"
          }
        ]
      }
    },
    "/Patient/{rid}": {
      "summary": "Read/Write/etc resource instance of type Patient",
      "description": "Access to services to manage the state of a single resource of type Patient",
      "get": {
        "summary": "Read the current state of the resource",
        "operationId": "readPatient",
        "responses": {
          "default": {
            "description": "Error, with details",
            "content": {
              "application/fhir+json": {
                "schema": {
                  "$ref": "https://hl7.org/fhir/R4/fhir.schema.json#/definitions/OperationOutcome"
                }
              }
            }
          },
          "200": {
            "description": "the resource being returned",
            "headers": {
              "ETag": {
                "description": "Version from Resource.meta.version as a weak ETag",
                "schema": {
                  "type": "string"
                }
              }
            },
            "content": {
              "application/fhir+json": {
                "schema": {
                  "$ref": "https://hl7.org/fhir/R4/fhir.schema.json#/definitions/Patient"
                }
              }
            }
          }
        },
        "parameters": [
          {
            "$ref": "#/components/parameters/rid"
          },
          {
            "$ref": "#/components/parameters/summary"
          },
          {
            "$ref": "#/components/parameters/format"
          },
          {
            "$ref": "#/components/parameters/pretty"
          },
          {
            "$ref": "#/components/parameters/elements"
          }
        ]
      }
    },
    "/Practitioner/{rid}": {
      "summary": "Read/Write/etc resource instance of type Practitioner",
      "description": "Access to services to manage the state of a single resource of type Practitioner",
      "get": {
        "summary": "Read the current state of the resource",
        "operationId": "readPractitioner",
        "responses": {
          "default": {
            "description": "Error, with details",
            "content": {
              "application/fhir+json": {
                "schema": {
                  "$ref": "https://hl7.org/fhir/R4/fhir.schema.json#/definitions/OperationOutcome"
                }
              }
            }
          },
          "200": {
            "description": "the resource being returned",
            "headers": {
              "ETag": {
                "description": "Version from Resource.meta.version as a weak ETag",
                "schema": {
                  "type": "string"
                }
              }
            },
            "content": {
              "application/fhir+json": {
                "schema": {
                  "$ref": "https://hl7.org/fhir/R4/fhir.schema.json#/definitions/Practitioner"
                }
              }
            }
          }
        },
        "parameters": [
          {
            "$ref": "#/components/parameters/rid"
          },
          {
            "$ref": "#/components/parameters/summary"
          },
          {
            "$ref": "#/components/parameters/format"
          },
          {
            "$ref": "#/components/parameters/pretty"
          },
          {
            "$ref": "#/components/parameters/elements"
          }
        ]
      }
    },
    "/Encounter/{rid}": {
      "summary": "Read/Write/etc resource instance of type Encounter",
      "description": "Access to services to manage the state of a single resource of type Encounter",
      "get": {
        "summary": "Read the current state of the resource",
        "operationId": "readEncounter",
        "responses": {
          "default": {
            "description": "Error, with details",
            "content": {
              "application/fhir+json": {
                "schema": {
                  "$ref": "https://hl7.org/fhir/R4/fhir.schema.json#/definitions/OperationOutcome"
                }
              }
            }
          },
          "200": {
            "description": "the resource being returned",
            "headers": {
              "ETag": {
                "description": "Version from Resource.meta.version as a weak ETag",
                "schema": {
                  "type": "string"
                }
              }
            },
            "content": {
              "application/fhir+json": {
                "schema": {
                  "$ref": "https://hl7.org/fhir/R4/fhir.schema.json#/definitions/Encounter"
                }
              }
            }
          }
        },
        "parameters": [
          {
            "$ref": "#/components/parameters/rid"
          },
          {
            "$ref": "#/components/parameters/summary"
          },
          {
            "$ref": "#/components/parameters/format"
          },
          {
            "$ref": "#/components/parameters/pretty"
          },
          {
            "$ref": "#/components/parameters/elements"
          }
        ]
      }
    },
    "/Condition": {
      "summary": "manage the collection of resources of type Condition",
      "description": "Access to services to manage the collection of all resources of type Condition",
      "get": {
        "summary": "Search all resources of type Condition based on a set of criteria",
        "operationId": "searchCondition",
        "responses": {
          "default": {
            "description": "Error, with details",
            "content": {
              "application/fhir+json": {
                "schema": {
                  "$ref": "https://hl7.org/fhir/R4/fhir.schema.json#/definitions/OperationOutcome"
                }
              }
            }
          },
          "200": {
            "description": "the resource being returned",
            "content": {
              "application/fhir+json": {
                "schema": {
                  "$ref": "https://hl7.org/fhir/R4/fhir.schema.json#/definitions/Bundle"
                }
              }
            }
          }
        },
        "parameters": [
          {
            "$ref": "#/components/parameters/format"
          },
          {
            "$ref": "#/components/parameters/pretty"
          },
          {
            "$ref": "#/components/parameters/summary"
          },
          {
            "$ref": "#/components/parameters/elements"
          },
          {
            "name": "patient",
            "in": "query",
            "description": "Multiple Resources: \r\n\r\n* [AllergyIntolerance](allergyintolerance.html): Who the sensitivity is for\r\n* [CarePlan](careplan.html): Who the care plan is for\r\n* [CareTeam](careteam.html): Who care team is for\r\n* [ClinicalImpression](clinicalimpression.html): Patient or group assessed\r\n* [Composition](composition.html): Who and/or what the composition is about\r\n* [Condition](condition.html): Who has the condition?\r\n* [Consent](consent.html): Who the consent applies to\r\n* [DetectedIssue](detectedissue.html): Associated patient\r\n* [DeviceRequest](devicerequest.html): Individual the service is ordered for\r\n* [DeviceUseStatement](deviceusestatement.html): Search by subject - a patient\r\n* [DiagnosticReport](diagnosticreport.html): The subject of the report if a patient\r\n* [DocumentManifest](documentmanifest.html): The subject of the set of documents\r\n* [DocumentReference](documentreference.html): Who/what is the subject of the document\r\n* [Encounter](encounter.html): The patient or group present at the encounter\r\n* [EpisodeOfCare](episodeofcare.html): The patient who is the focus of this episode of care\r\n* [FamilyMemberHistory](familymemberhistory.html): The identity of a subject to list family member history items for\r\n* [Flag](flag.html): The identity of a subject to list flags for\r\n* [Goal](goal.html): Who this goal is intended for\r\n* [ImagingStudy](imagingstudy.html): Who the study is about\r\n* [Immunization](immunization.html): The patient for the vaccination record\r\n* [List](list.html): If all resources have the same subject\r\n* [MedicationAdministration](medicationadministration.html): The identity of a patient to list administrations  for\r\n* [MedicationDispense](medicationdispense.html): The identity of a patient to list dispenses  for\r\n* [MedicationRequest](medicationrequest.html): Returns prescriptions for a specific patient\r\n* [MedicationStatement](medicationstatement.html): Returns statements for a specific patient.\r\n* [NutritionOrder](nutritionorder.html): The identity of the person who requires the diet, formula or nutritional supplement\r\n* [Observation](observation.html): The subject that the observation is about (if patient)\r\n* [Procedure](procedure.html): Search by subject - a patient\r\n* [RiskAssessment](riskassessment.html): Who/what does assessment apply to?\r\n* [ServiceRequest](servicerequest.html): Search by subject - a patient\r\n* [SupplyDelivery](supplydelivery.html): Patient for whom the item is supplied\r\n* [VisionPrescription](visionprescription.html): The identity of a patient to list dispenses for\r\n",
            "schema": {
              "type": "string"
            }
          },
          {
            "name": "clinical-status",
            "in": "query",
            "description": "The clinical status of the condition",
            "schema": {
              "type": "string"
            }
          }
        ]
      }
    },
    "/Observation": {
      "summary": "manage the collection of resources of type Observation",
      "description": "Access to services to manage the collection of all resources of type Observation",
      "get": {
        "summary": "Search all resources of type Observation based on a set of criteria",
        "operationId": "searchObservation",
        "responses": {
          "default": {
            "description": "Error, with details",
            "content": {
              "application/fhir+json": {
                "schema": {
                  "$ref": "https://hl7.org/fhir/R4/fhir.schema.json#/definitions/OperationOutcome"
                }
              }
            }
          },
          "200": {
            "description": "the resource being returned",
            "content": {
              "application/fhir+json": {
                "schema": {
                  "$ref": "https://hl7.org/fhir/R4/fhir.schema.json#/definitions/Bundle"
                }
              }
            }
          }
        },
        "parameters": [
          {
            "$ref": "#/components/parameters/format"
          },
          {
            "$ref": "#/components/parameters/pretty"
          },
          {
            "$ref": "#/components/parameters/summary"
          },
          {
            "$ref": "#/components/parameters/elements"
          },
          {
            "name": "patient",
            "in": "query",
            "description": "Multiple Resources: \r\n\r\n* [AllergyIntolerance](allergyintolerance.html): Who the sensitivity is for\r\n* [CarePlan](careplan.html): Who the care plan is for\r\n* [CareTeam](careteam.html): Who care team is for\r\n* [ClinicalImpression](clinicalimpression.html): Patient or group assessed\r\n* [Composition](composition.html): Who and/or what the composition is about\r\n* [Condition](condition.html): Who has the condition?\r\n* [Consent](consent.html): Who the consent applies to\r\n* [DetectedIssue](detectedissue.html): Associated patient\r\n* [DeviceRequest](devicerequest.html): Individual the service is ordered for\r\n* [DeviceUseStatement](deviceusestatement.html): Search by subject - a patient\r\n* [DiagnosticReport](diagnosticreport.html): The subject of the report if a patient\r\n* [DocumentManifest](documentmanifest.html): The subject of the set of documents\r\n* [DocumentReference](documentreference.html): Who/what is the subject of the document\r\n* [Encounter](encounter.html): The patient or group present at the encounter\r\n* [EpisodeOfCare](episodeofcare.html): The patient who is the focus of this episode of care\r\n* [FamilyMemberHistory](familymemberhistory.html): The identity of a subject to list family member history items for\r\n* [Flag](flag.html): The identity of a subject to list flags for\r\n* [Goal](goal.html): Who this goal is intended for\r\n* [ImagingStudy](imagingstudy.html): Who the study is about\r\n* [Immunization](immunization.html): The patient for the vaccination record\r\n* [List](list.html): If all resources have the same subject\r\n* [MedicationAdministration](medicationadministration.html): The identity of a patient to list administrations  for\r\n* [MedicationDispense](medicationdispense.html): The identity of a patient to list dispenses  for\r\n* [MedicationRequest](medicationrequest.html): Returns prescriptions for a specific patient\r\n* [MedicationStatement](medicationstatement.html): Returns statements for a specific patient.\r\n* [NutritionOrder](nutritionorder.html): The identity of the person who requires the diet, formula or nutritional supplement\r\n* [Observation](observation.html): The subject that the observation is about (if patient)\r\n* [Procedure](procedure.html): Search by subject - a patient\r\n* [RiskAssessment](riskassessment.html): Who/what does assessment apply to?\r\n* [ServiceRequest](servicerequest.html): Search by subject - a patient\r\n* [SupplyDelivery](supplydelivery.html): Patient for whom the item is supplied\r\n* [VisionPrescription](visionprescription.html): The identity of a patient to list dispenses for\r\n",
            "schema": {
              "type": "string"
            }
          },
          {
            "name": "code",
            "in": "query",
            "description": "Multiple Resources: \r\n\r\n* [AllergyIntolerance](allergyintolerance.html): Code that identifies the allergy or intolerance\r\n* [Condition](condition.html): Code for the condition\r\n* [DeviceRequest](devicerequest.html): Code for what is being requested/ordered\r\n* [DiagnosticReport](diagnosticreport.html): The code for the report, as opposed to codes for the atomic results, which are the names on the observation resource referred to from the result\r\n* [FamilyMemberHistory](familymemberhistory.html): A search by a condition code\r\n* [List](list.html): What the purpose of this list is\r\n* [Medication](medication.html): Returns medications for a specific code\r\n* [MedicationAdministration](medicationadministration.html): Return administrations of this medication code\r\n* [MedicationDispense](medicationdispense.html): Returns dispenses of this medicine code\r\n* [MedicationRequest](medicationrequest.html): Return prescriptions of this medication code\r\n* [MedicationStatement](medicationstatement.html): Return statements of this medication code\r\n* [Observation](observation.html): The code of the observation type\r\n* [Procedure](procedure.html): A code to identify a  procedure\r\n* [ServiceRequest](servicerequest.html): What is being requested/ordered\r\n",
            "schema": {
              "type": "string"
            }
          },
          {
            "name": "_count",
            "in": "query",
            "description": "\u003cdiv\u003e \u003cp\u003eThe client and server \u003cstrong\u003eSHALL\u003c/strong\u003e support search result limiting.\u003c/p\u003e\u003c/div\u003e",
            "schema": {
              "type": "number"
            }
          },
          {
            "name": "_sort",
            "in": "query",
            "description": "\u003cdiv\u003e \u003cp\u003eThe client and server \u003cstrong\u003eSHALL\u003c/strong\u003e support search result sorting by date and \u003cstrong\u003eMAY\u003c/strong\u003e support other values.\u003c/p\u003e\u003c/div\u003e",
            "schema": {
              "type": "string"
            }
          }
        ]
      }
    },
    "/QuestionnaireResponse": {
      "summary": "Manager for resources of type QuestionnaireResponse",
      "description": "The Manager for resources of type QuestionnaireResponse: provides services to manage the collection of all the QuestionnaireResponse instances",
      "get": {
        "summary": "Search all resources of type QuestionnaireResponse based on a set of criteria",
        "operationId": "searchQuestionnaireResponse",
        "responses": {
          "default": {
            "description": "Error, with details",
            "content": {
              "application/fhir+json": {
                "schema": {
                  "$ref": "https://hl7.org/fhir/R4/fhir.schema.json#/definitions/OperationOutcome"
                }
              }
            }
          },
          "200": {
            "description": "the resource being returned",
            "content": {
              "application/fhir+json": {
                "schema": {
                  "$ref": "https://hl7.org/fhir/R4/fhir.schema.json#/definitions/Bundle"
                }
              }
            }
          }
        },
        "parameters": [
          {
            "$ref": "#/components/parameters/format"
          },
          {
            "$ref": "#/components/parameters/pretty"
          },
          {
            "$ref": "#/components/parameters/summary"
          },
          {
            "$ref": "#/components/parameters/elements"
          },
          {
            "name": "patient",
            "in": "query",
            "description": "The patient that is the subject of the questionnaire response",
            "schema": {
              "type": "string"
            }
          },
          {
            "name": "questionnaire",
            "in": "query",
            "description": "The questionnaire the answers are provided for",
            "schema": {
              "type": "string"
            }
          },
          {
            "name": "status",
            "in": "query",
            "description": "The status of the questionnaire response",
            "schema": {
              "type": "string"
            }
          },
          {
            "name": "_count",
            "in": "query",
            "description": "\u003cdiv\u003e \u003cp\u003eThe client and server \u003cstrong\u003eSHALL\u003c/strong\u003e support search result limiting.\u003c/p\u003e\u003c/div\u003e",
            "schema": {
              "type": "number"
            }
          },
          {
            "name": "_sort",
            "in": "query",
            "description": "\u003cdiv\u003e \u003cp\u003eThe client and server \u003cstrong\u003eSHALL\u003c/strong\u003e support search result sorting by authored and \u003cstrong\u003eMAY\u003c/strong\u003e support other values.\u003c/p\u003e\u003c/div\u003e",
            "schema": {
              "type": "string"
            }
          }
        ]
      },
      "post": {
        "summary": "Create a new resource",
        "operationId": "createQuestionnaireResponse",
        "requestBody": {
          "description": "The new state of the resource",
          "required": true,
          "content": {
            "application/fhir+json": {
              "schema": {
                "$ref": "https://hl7.org/fhir/R4/fhir.schema.json#/definitions/QuestionnaireResponse"
              }
            }
          }
        },
        "responses": {
          "default": {
            "description": "Error, with details",
            "content": {
              "application/fhir+json": {
                "schema": {
                  "$ref": "https://hl7.org/fhir/R4/fhir.schema.json#/definitions/OperationOutcome"
                }
              }
            }
          },
          "200": {
            "description": "the resource being returned after being updated",
            "headers": {
              "ETag": {
                "description": "Version from Resource.meta.version as a weak ETag",
                "schema": {
                  "type": "string"
                }
              }
            },
            "content": {
              "application/fhir+json": {
                "schema": {
                  "$ref": "https://hl7.org/fhir/R4/fhir.schema.json#/definitions/QuestionnaireResponse"
                }
              }
            }
          }
        },
        "parameters": [
          {
            "$ref": "#/components/parameters/summary"
          },
          {
            "$ref": "#/components/parameters/format"
          },
          {
            "$ref": "#/components/parameters/pretty"
          },
          {
            "$ref": "#/components/parameters/elements"
          }
        ]
      }
    },
    "/QuestionnaireResponse/{rid}": {
      "summary": "Read/Write/etc resource instance of type QuestionnaireResponse",
      "description": "Access to services to manage the state of a single resource of type QuestionnaireResponse",
      "get": {
        "summary": "Read the current state of the resource",
        "operationId": "readQuestionnaireResponse",
        "responses": {
          "default": {
            "description": "Error, with details",
            "content": {
              "application/fhir+json": {
                "schema": {
                  "$ref": "https://hl7.org/fhir/R4/fhir.schema.json#/definitions/OperationOutcome"
                }
              }
            }
          },
          "200": {
            "description": "the resource being returned",
            "headers": {
              "ETag": {
                "description": "Version from Resource.meta.version as a weak ETag",
                "schema": {
                  "type": "string"
                }
              }
            },
            "content": {
              "application/fhir+json": {
                "schema": {
                  "$ref": "https://hl7.org/fhir/R4/fhir.schema.json#/definitions/QuestionnaireResponse"
                }
              }
            }
          }
        },
        "parameters": [
          {
            "$ref": "#/components/parameters/rid"
          },
          {
            "$ref": "#/components/parameters/summary"
          },
          {
            "$ref": "#/components/parameters/format"
          },
          {
            "$ref": "#/components/parameters/pretty"
          },
          {
            "$ref": "#/components/parameters/elements"
          }
        ]
      },
      "put": {
        "summary": "Update the current state of the resource",
        "operationId": "updateQuestionnaireResponse",
        "requestBody": {
          "description": "The new state of the resource",
          "required": true,
          "content": {
            "application/fhir+json": {
              "schema": {
                "$ref": "https://hl7.org/fhir/R4/fhir.schema.json#/definitions/QuestionnaireResponse"
              }
            }
          }
        },
        "responses": {
          "default": {
            "description": "Error, with details",
            "content": {
              "application/fhir+json": {
                "schema": {
                  "$ref": "https://hl7.org/fhir/R4/fhir.schema.json#/definitions/OperationOutcome"
                }
              }
            }
          },
          "200": {
            "description": "the resource being returned after being updated",
            "headers": {
              "ETag": {
                "description": "Version from Resource.meta.version as a weak ETag",
                "schema": {
                  "type": "string"
                }
              }
            },
            "content": {
              "application/fhir+json": {
                "schema": {
                  "$ref": "https://hl7.org/fhir/R4/fhir.schema.json#/definitions/QuestionnaireResponse"
                }
              }
            }
          }
        },
        "parameters": [
          {
            "$ref": "#/components/parameters/rid"
          },
          {
            "$ref": "#/components/parameters/summary"
          },
          {
            "$ref": "#/components/parameters/format"
          },
          {
            "$ref": "#/components/parameters/pretty"
          },
          {
            "$ref": "#/components/parameters/elements"
          }
        ]
      }
    }
  },
  "components": {
    "parameters": {
      "rid": {
        "name": "rid",
        "in": "path",
        "description": "id of the resource (\u003dResource.id)",
        "required": true,
        "allowEmptyValue": false,
        "style": "simple",
        "schema": {
          "type": "string"
        }
      },
      "hid": {
        "name": "hid",
        "in": "path",
        "description": "id of the history entry (\u003dResource.meta.versionId)",
        "required": true,
        "allowEmptyValue": false,
        "style": "simple",
        "schema": {
          "type": "string"
        }
      },
      "summary": {
        "name": "_summary",
        "in": "query",
        "description": "Requests the server to return a designated subset of the resource",
        "allowEmptyValue": true,
        "style": "form",
        "schema": {
          "type": "string",
          "enum": [
            "true",
            "text",
            "data",
            "count",
            "false"
          ]
        }
      },
      "format": {
        "name": "_format",
        "in": "query",
        "description": "Specify alternative response formats by their MIME-types (when a client is unable acccess accept: header)",
        "allowEmptyValue": true,
        "style": "form",
        "schema": {
          "type": "string",
          "format": "mime-type"
        }
      },
      "pretty": {
        "name": "_pretty",
        "in": "query",
        "description": "Ask for a pretty printed response for human convenience",
        "allowEmptyValue": true,
        "style": "form",
        "schema": {
          "type": "boolean"
        }
      },
      "elements": {
        "name": "_elements",
        "in": "query",
        "description": "Requests the server to return a collection of elements from the resource",
        "allowEmptyValue": true,
        "style": "form",
        "explode": false,
        "schema": {
          "type": "array",
          "format": "string",
          "items": {
            "format": "string"
          }
        }
      },
      "count": {
        "name": "_count",
        "in": "query",
        "description": "The maximum number of search results on a page. The server is not bound to return the number requested, but cannot return more",
        "schema": {
          "type": "number"
        }
      }
    }
  }
}